GoConf/__init__.py
GoConf/goconfigure.py
goconfigure-0.1.5.dist-info/METADATA
goconfigure-0.1.5.dist-info/WHEEL
goconfigure-0.1.5.dist-info/top_level.txt
goconfigure-0.1.5.dist-info/RECORD
